diffdrrdata/__init__.py
diffdrrdata/_modidx.py
diffdrrdata/deepfluoro.py
diffdrrdata/ljubljana.py
diffdrrdata/utils.py
diffdrrdata-0.0.7.dist-info/LICENSE
diffdrrdata-0.0.7.dist-info/METADATA
diffdrrdata-0.0.7.dist-info/WHEEL
diffdrrdata-0.0.7.dist-info/entry_points.txt
diffdrrdata-0.0.7.dist-info/top_level.txt
diffdrrdata-0.0.7.dist-info/RECORD
