Metadata-Version: 2.1
Name: diffdrrdata
Version: 0.0.7
Summary: Open-source 2D/3D registration datasets and dataloaders for DiffDRR
Home-page: https://github.com/eigenvivek/DiffDRR-Datasets
Author: Vivek Gopalakrishnan
Author-email: vivekg@mit.edu
License: Apache Software License 2.0
Keywords: nbdev jupyter notebook python
Classifier: Development Status :: 4 - Beta
Classifier: Intended Audience :: Developers
Classifier: Natural Language :: English
Classifier: Programming Language :: Python :: 3.7
Classifier: Programming Language :: Python :: 3.8
Classifier: Programming Language :: Python :: 3.9
Classifier: Programming Language :: Python :: 3.10
Classifier: License :: OSI Approved :: Apache Software License
Requires-Python: >=3.7
License-File: LICENSE
Requires-Dist: diffdrr >=0.5.0rc0
Requires-Dist: h5py
Provides-Extra: dev
